Hardware/Design/AHBspi_master.v
`timescale 1ns / 1ns

module AHBspi_master(
			// Bus signals
			input wire HCLK,			// bus clock
			input wire HRESETn,			// bus reset, active low
			input wire HSEL,			// selects this slave
			input wire HREADY,			// indicates previous transaction completing
			input wire [31:0] HADDR,	// address
			input wire [1:0] HTRANS,	// transaction type (only bit 1 used)
			input wire HWRITE,			// write transaction
//			input wire [2:0] HSIZE,		// transaction width ignored
			input wire [31:0] HWDATA,	// write data
			output wire [31:0] HRDATA,	// read data from slave
            output reg MOSI,           // to slaves
            output wire SCLK,           // to slaves
			input wire MISO,            // from selected slave
            output wire ACCELEROMETER_SELECT_N,	// to accelerometer slave
            output wire HREADYOUT		
    );
	
	// Registers to hold signals from address phase
	reg [1:0] rHADDR;	// only need two bits of address
	reg rWrite;	// write enable signals
	wire send = (rWrite && (rHADDR == 2'b01) && ~busy);

 	// Capture bus signals in address phase
	always @(posedge HCLK)
		if(!HRESETn)
			begin
				rHADDR <= 2'b0;
				rWrite <= 1'b0;
			end
		else if(HREADY)
		 begin
			rHADDR <= HADDR[3:2];                   // capture address bits for for use in data phase
			rWrite <= HSEL & HWRITE & HTRANS[1];	// slave selected for write transfer       
		 end

    assign HREADYOUT = 1'b1;
    // COUNT is an 8 bit counter where 
    // COUNT[6:4] are used to select MOSI and MISO bits
    // Also, busy and SCLK wires epend on COUNT[7] and COUNT[3] respectively

    wire busy;
    assign busy = ~COUNT[7];
    assign SCLK = COUNT[3];

    reg [7:0] NEXT_COUNT;
	reg [7:0] COUNT;	// holds interrupt enable bits
	
	wire shift = (COUNT[3:0] == 4'b0111);	// shift at posedge of SCLK

	always @(posedge HCLK)
	begin
       if (!HRESETn) COUNT <= 8'h80;  // reset to max value
       else COUNT <= NEXT_COUNT;
     end
	 
	always @( * )
	begin
       if (busy) NEXT_COUNT = COUNT + 1'b1;
	   else if (send) NEXT_COUNT = 8'b0;
	   else NEXT_COUNT = 8'h80;
    end
		
		
	// SPICON register
    reg ACCELEROMETER_SELECT_REG;
	wire [7:0] SPICON;	// holds interrupt enable bits

	always @(posedge HCLK)
	begin
        if (!HRESETn) 
            begin
                ACCELEROMETER_SELECT_REG <= 1'b0;    
            end
        else
            begin
                if (rWrite && (rHADDR == 2'b00) && ~busy) ACCELEROMETER_SELECT_REG <= HWDATA[0]; 
            end
     end
	 
	 assign SPICON = {busy, 6'b0, ACCELEROMETER_SELECT_REG};

    assign ACCELEROMETER_SELECT_N = ~ACCELEROMETER_SELECT_REG;

	// TX
	reg [7:0] TX_DATA;	// holds interrupt enable bits

	
	
	always @(posedge HCLK)
        if (!HRESETn) TX_DATA <= 8'b0;   
        else if (send) TX_DATA <= HWDATA[7:0]; 
    
    always @( * )
        case (COUNT[6:4])
            3'b000:  MOSI = TX_DATA[7];
            3'b001:  MOSI = TX_DATA[6];
            3'b010:  MOSI = TX_DATA[5];
            3'b011:  MOSI = TX_DATA[4];
            3'b100:  MOSI = TX_DATA[3];
            3'b101:  MOSI = TX_DATA[2];
            3'b110:  MOSI = TX_DATA[1];
            3'b111:  MOSI = TX_DATA[0];
        endcase

    // Read data
    reg [7:0] READ_DATA;
    reg[7:0] SHIFT_REG;
    
    always @( * )
    begin
        case (rHADDR)
            2'b00:  READ_DATA = SPICON;
            2'b01:  READ_DATA = TX_DATA;
            2'b10:  READ_DATA = SHIFT_REG;
            2'b11:  READ_DATA = SPICON;
        endcase
        
     end
     
     assign HRDATA = {24'b0, READ_DATA};
	
	
	
	// shift register	
	always @(posedge HCLK)
	begin
	if (!HRESETn) SHIFT_REG <= 8'b0;
	else if (shift) SHIFT_REG <= {SHIFT_REG[6:0],MISO};
	end

endmodule

Hardware/Testbench/TB_AHBspimaster.v
`timescale 1ns / 1ns
/////////////////////////////////////////////////////////////////
// Module Name: TB_AHBuart - testbench for AHB uart block
/////////////////////////////////////////////////////////////////
module TB_AHBspimaster(    );

// AHB-Lite Bus Signals
	reg HCLK;					// bus clock
	reg HRESETn;				// bus reset, active low
	reg HSELx = 1'b0;			// selects this slave
	reg [31:0] HADDR = 32'h0;	// address
	reg [1:0] HTRANS = 2'b0;	// transaction type (only two tpyes used)
	reg HWRITE = 1'b0;			// write transaction
	reg [2:0] HSIZE = 3'b0;		// transaction width (max 32-bit supported)
	reg [31:0] HWDATA = 32'h0;	// write data
	reg [2:0] HBURST = 3'b0;	// burst type
	reg [3:0] HPROT = 4'b0011;	// privileged data transfer
	wire [31:0] HRDATA;			// read data from slave
    wire HREADY;             	// ready signal - to master and to all slaves
    wire HREADYOUT;             // ready signal output from this slave
	wire MOSI;
	wire SCLK;
	wire CS;

// Integer is used in for loops
	integer i = 0;

// Define names for some of the bus signal values and for the device registers
	localparam [2:0] BYTE = 3'b000, HALF = 3'b001, WORD = 3'b010;	// HSIZE values
	localparam [1:0] IDLE = 2'b00, NONSEQ = 2'b10;					// HTRANS values
	localparam [31:0] RXDATA = 32'h8, TXDATA = 32'h4, SPI_CTRL = 32'h0;	// registers 

// Instantiate the design under test and connect it to the testbench signals
// Some bus signals are not used - this design ignores HSIZE, for example
	AHBspi_master dut(
		.HCLK(HCLK),
		.HRESETn(HRESETn),
		.HSEL(HSELx),
		.HREADY(HREADY),
		.HADDR(HADDR),
		.HTRANS(HTRANS),
		.HWRITE(HWRITE),  
		.HWDATA(HWDATA),  
		.HRDATA(HRDATA),  
		.MOSI(MOSI),
		.SCLK(SCLK),
		.MISO(MOSI),
		.ACCELEROMETER_SELECT_N(CS),
		.HREADYOUT(HREADYOUT)
		);

// Generate the clock signal at 50 MHz - period 20 ns
	initial
		begin
			HCLK = 1'b0;
			forever
				#10 HCLK = ~HCLK;  // invert clock every 10 ns
		end

// Generate reset pulse and simulate some bus transactions
	initial
		begin
			HRESETn = 1'b1;			// reset inactive at start
			#20 HRESETn = 1'b0;		// reset active on falling edge of clock
			#20 HRESETn = 1'b1;		// inactive after one clock cycle
			#50;					// delay to see what happens
			
			// after reset read register values
			AHBread(WORD, SPI_CTRL, 32'h0);
			AHBread(WORD, TXDATA, 32'h0);
			AHBread(WORD, RXDATA, 32'h0);
			
			AHBidle;	// need to put bus in idle state unless there is another transaction following
			#20;		// leave a short gap
		
			// Read/write tests on registers
			AHBwrite(WORD, SPI_CTRL, 32'h1);
			AHBread(WORD, SPI_CTRL, 32'h1);
			AHBwrite(WORD, TXDATA, 32'h16);
			AHBread(WORD, TXDATA, 32'h16);
			AHBread(WORD, SPI_CTRL, 32'h81);			
			AHBidle;
			#3500;							// delay to allow actions to complete
			AHBread(WORD, SPI_CTRL, 32'h1);
            AHBread(WORD, RXDATA, 32'h16);	
            AHBwrite(WORD, SPI_CTRL, 32'h0);
			AHBidle;
            #500;
			$stop;							// stop the simulation
		end


// =========== AHB bus tasks - crude models of bus activity =========================
// To use these tasks, include everything below this line, until the next ===== line
// Read and Write tasks do not restore the bus to idle, as another transaction might follow.
// Use Idle task immediately after read or write if no transaction follows immediately.

    reg [31:0] nextWdata = 32'h0;        // delayed data for write transactions
    reg [31:0] expectRdata = 32'h0;        // expected read data for read transactions
    reg [31:0] rExpectRead;                // store expected read data
    reg checkRead;                        // remember that read is in progress
    reg transState;                        // state of our transaction - 1 if in data phase
    reg error = 1'b0;  // read error signal - asserted for one cycle AFTER read completes
    integer errCount = 0;                // error counter
    
// Task to simulate a write transaction on AHB Lite
    task AHBwrite ( 
            input [2:0] size,    // transaction width - BYTE, HALF or WORD
            input [31:0] addr,    // address
            input [31:0] data );    // data to be written
        begin
            wait (HREADY == 1'b1);    // wait for ready signal - previous transaction completing
            @ (posedge HCLK);    // align with clock
            #1 HSIZE = size;    // set up signals for address phase, just after clock edge
            HTRANS = NONSEQ;    // transaction type non-sequential
            HWRITE = 1'b1;        // write transaction
            HADDR = addr;        // put address on bus
            HSELx = 1'b1;        // select this slave
            #1 nextWdata = data;    // a little later, store data for use in the data phase
        end
    endtask

// Task to simulate a read transaction on AHB Lite
    task AHBread (
            input [2:0] size,    // transaction width - BYTE, HALF or WORD
            input [31:0] addr,    // address
            input [31:0] data );    // expected data from slave
        begin  
            wait (HREADY == 1'b1);    // wait for ready signal - previous transaction completing
            @ (posedge HCLK);    // align with clock
            #1 HSIZE = size;    // set up signals for address phase, just after clock edge
            HTRANS = NONSEQ;    // transaction type non-sequential
            HWRITE = 1'b0;        // read transaction
            HADDR = addr;        // put address on bus
            HSELx = 1'b1;        // select this slave
            #1 expectRdata = data;    // a little later, store expected data for checking in the data phase
        end
    endtask

// Task to put bus in idle state after read or write transaction
    task AHBidle;
        begin  
            wait (HREADY == 1'b1); // wait for ready signal - previous transaction completing
            @ (posedge HCLK);    // then wait for clock edge
            #1 HTRANS = IDLE;    // set transaction type to idle
            HSELx = 1'b0;        // deselect the slave
        end
    endtask

// Control the HWDATA signal during the data phase
    always @ (posedge HCLK)
        if (~HRESETn) HWDATA <= 32'b0;
        else if (HSELx && HWRITE && HTRANS && HREADY) // our write transaction is moving to data phase
            #1 HWDATA <= nextWdata;    // change HWDATA shortly after the clock edge
        else if (HREADY)    // some other transaction in progress
            #1 HWDATA <= {HADDR[31:24], HADDR[11:0], 12'hbad}; // put rubbish on HWDATA

// Register to hold expected read data during data phase, and flag to indicate that read is in progress
    always @ (posedge HCLK)
        if (~HRESETn)
            begin
                rExpectRead <= 32'b0;
                checkRead <= 1'b0;
            end
        else if (HSELx && ~HWRITE && HTRANS && HREADY)  // our read transaction moving to data phase
            begin
                rExpectRead <= expectRdata;    // update register with expected data
                checkRead <=1'b1;            // set flag to get it checked
            end
        else if (HREADY)    // some other transaction moving to data phase
                checkRead <= 1'b0;            // clear flag - no check needed

// Check the read data as the read transaction completes
// error signal will be asserted for one cycle AFTER problem detected
    always @ (posedge HCLK)
        if (~HRESETn) error <= 1'b0;
        else if (checkRead & HREADY)    // our read transaction is completing on this clock edge
            if (HRDATA != rExpectRead)    // the read data is not as expected
                begin
                    error <= 1'b1;        // so flag this as an error
                    errCount = errCount + 1;    // and increment the error counter
                end
            else error <= 1'b0;            // otherwise our read transaction is OK
        else        // this is some other transaction 
            error <= 1'b0;    // so no error 
            
// Control the HREADY signal during the data phase
    always @ (posedge HCLK)
        if (~HRESETn) transState <= 1'b0;    // after reset, this is not the data phase of our transaction
        else if (HSELx && HTRANS && HREADY) // transaction with this slave is moving to data phase
            #1 transState <= 1'b1;            // so this slave controls HREADY
        else if (HREADY)                    // some other transaction is moving to data phase
            #1 transState <= 1'b0;            // some other slave controls HREADY
            
    assign HREADY = transState ? HREADYOUT : 1'b1;     // other slave is always ready

//============================= END of AHB bus tasks =========================================
 initial begin
 $dumpfile("dump.vcd");
 $dumpvars(2);
 end
 
endmodule

Hardware/DemoSystem.sim/sim_top/behav/dump.vcd
$date
   Thu Apr 21 11:33:27 2022
$end
$version
  13.1
$end
$timescale
  1ps
$end
$scope module TB_AHBspimaster $end
$var reg 1 ! HCLK $end
$var reg 1 " HRESETn $end
$var reg 1 # HSELx $end
$var reg 32 $ HADDR [31:0] $end
$var reg 2 % HTRANS [1:0] $end
$var reg 1 & HWRITE $end
$var reg 3 ' HSIZE [2:0] $end
$var reg 32 ( HWDATA [31:0] $end
$var reg 3 ) HBURST [2:0] $end
$var reg 4 * HPROT [3:0] $end
$var wire 32 + HRDATA [31:0] $end
$var wire 1 , HREADY $end
$var wire 1 - HREADYOUT $end
$var wire 1 . MOSI $end
$var wire 1 / SCLK $end
$var wire 1 0 CS $end
$var integer 32 1 i $end
$var reg 32 2 nextWdata [31:0] $end
$var reg 32 3 expectRdata [31:0] $end
$var reg 32 4 rExpectRead [31:0] $end
$var reg 1 5 checkRead $end
$var reg 1 6 transState $end
$var reg 1 7 error $end
$var integer 32 8 errCount $end
$var parameter 3 9 BYTE [2:0] $end
$var parameter 3 : HALF [2:0] $end
$var parameter 3 ; WORD [2:0] $end
$var parameter 2 < IDLE [1:0] $end
$var parameter 2 = NONSEQ [1:0] $end
$var parameter 32 > RXDATA [31:0] $end
$var parameter 32 ? TXDATA [31:0] $end
$var parameter 32 @ SPI_CTRL [31:0] $end
$scope module dut $end
$var wire 1 A HCLK $end
$var wire 1 B HRESETn $end
$var wire 1 C HSEL $end
$var wire 1 D HREADY $end
$var wire 32 E HADDR [31:0] $end
$var wire 2 F HTRANS [1:0] $end
$var wire 1 G HWRITE $end
$var wire 32 H HWDATA [31:0] $end
$var wire 32 I HRDATA [31:0] $end
$var reg 1 J MOSI $end
$var wire 1 K SCLK $end
$var wire 1 L MISO $end
$var wire 1 M ACCELEROMETER_SELECT_N $end
$var wire 1 N HREADYOUT $end
$var reg 2 O rHADDR [1:0] $end
$var reg 1 P rWrite $end
$var wire 1 Q send $end
$var wire 1 R busy $end
$var reg 8 S NEXT_COUNT [7:0] $end
$var reg 8 T COUNT [7:0] $end
$var wire 1 U shift $end
$var reg 1 V ACCELEROMETER_SELECT_REG $end
$var wire 8 W SPICON [7:0] $end
$var reg 8 X TX_DATA [7:0] $end
$var reg 8 Y READ_DATA [7:0] $end
$var reg 8 Z SHIFT_REG [7:0] $end
$upscope $end
$scope task AHBwrite $end
$var reg 3 [ size [2:0] $end
$var reg 32 \ addr [31:0] $end
$var reg 32 ] data [31:0] $end
$upscope $end
$scope task AHBread $end
$var reg 3 ^ size [2:0] $end
$var reg 32 _ addr [31:0] $end
$var reg 32 ` data [31:0] $end
$upscope $end
$scope task AHBidle $end
$upscope $end
$upscope $end
$enddefinitions $end
#0
$dumpvars
0!
1"
0#
b0 $
b0 %
0&
b0 '
b0 (
b0 )
b11 *
b0xxxxxxxx +
1,
1-
x.
x/
x0
b0 1
b0 2
b0 3
bx 4
x5
x6
07
b0 8
b0 9
b1 :
b10 ;
b0 <
b10 =
b1000 >
b100 ?
b0 @
0A
1B
0C
1D
b0 E
b0 F
0G
b0 H
b0xxxxxxxx I
xJ
xK
xL
xM
1N
bx O
xP
xQ
xR
bx S
bx T
xU
xV
bx000000x W
bx X
bx Y
bx Z
bx [
bx \
bx ]
bx ^
bx _
bx `
$end
#10000
1!
b0x000000x +
05
07
1A
b0x000000x I
b0 O
0P
0Q
b10000000 S
bx T
bx000000x Y
#11000
b101110101101 (
1,
06
1D
b101110101101 H
#20000
0!
0"
0A
0B
#30000
1!
b0 (
b0 +
0.
0/
10
b0 4
05
06
07
1A
b0 H
b0 I
0J
0K
0L
1M
b0 O
0P
0Q
0R
b10000000 S
b10000000 T
0U
0V
b0 W
b0 X
b0 Y
b0 Z
#40000
0!
1"
0A
1B
#50000
1!
05
07
1A
b0 O
0P
b10000000 T
#51000
b101110101101 (
06
b101110101101 H
#60000
0!
0A
#70000
1!
05
07
1A
b0 O
0P
b10000000 T
#71000
b101110101101 (
06
#80000
0!
0A
#90000
1!
05
07
1A
b0 O
0P
b10000000 T
b10 ^
b0 _
b0 `
#91000
1#
b0 $
b10 %
b10 '
b101110101101 (
06
1C
b10 F
#92000
b0 3
b10 ^
b100 _
b0 `
#100000
0!
0A
#110000
1!
b0 4
15
07
1A
b0 O
0P
b10000000 T
#111000
b100 $
b10 %
b10 '
b100101110101101 (
1,
16
1D
b100 E
b100101110101101 H
#112000
b0 3
b10 ^
b1000 _
b0 `
#120000
0!
0A
#130000
1!
b0 4
15
07
1A
b1 O
0P
0Q
b10000000 T
b0 Y
#131000
b1000 $
b10 %
b10 '
b1000101110101101 (
16
b1000 E
b1000101110101101 H
#132000
b0 3
#140000
0!
0A
#150000
1!
b0 4
15
07
1A
b10 O
0P
0Q
b10000000 T
b0 Y
#151000
0#
b0 %
b1000101110101101 (
16
0C
b0 F
#160000
0!
0A
#170000
1!
05
07
1A
b10 O
0P
b10000000 T
#171000
b1000101110101101 (
1,
06
1D
b10 [
b0 \
b1 ]
#180000
0!
0A
#190000
1!
05
07
1A
b10 O
0P
b10000000 T
#191000
1#
b0 $
b10 %
1&
b10 '
b101110101101 (
06
1C
b0 E
b10 F
1G
b101110101101 H
#192000
b1 2
b10 ^
b0 _
b1 `
#200000
0!
0A
#210000
1!
05
07
1A
b0 O
1P
0Q
b10000000 T
b0 Y
#211000
b0 $
b10 %
0&
b10 '
b1 (
1,
16
1D
0G
b1 H
#212000
b1 3
b10 [
b100 \
b10110 ]
#220000
0!
0A
#230000
1!
b1 +
00
b1 4
15
07
1A
b1 I
0M
b0 O
0P
0Q
b10000000 T
1V
b1 W
b1 Y
#231000
b100 $
b10 %
1&
b10 '
b100101110101101 (
16
b100 E
1G
b100101110101101 H
#232000
b10110 2
b10 ^
b100 _
b10110 `
#240000
0!
0A
#250000
1!
b0 +
05
07
1A
b0 I
b1 O
1P
1Q
b0 S
b10000000 T
b0 Y
#251000
b100 $
b10 %
0&
b10 '
b10110 (
16
0G
b10110 H
#252000
b10110 3
b10 ^
b0 _
b10000001 `
#260000
0!
0A
#270000
1!
b10110 +
b10110 4
15
07
1A
b10110 I
0J
b1 O
0P
0Q
1R
b1 S
b0 T
b10000001 W
b10110 X
b10110 Y
#271000
b0 $
b10 %
b10 '
b101110101101 (
16
b0 E
b101110101101 H
#272000
b10000001 3
#280000
0!
0A
#290000
1!
b10000001 +
b10000001 4
15
07
1A
b10000001 I
0J
b0 O
0P
0Q
b10 S
b1 T
0U
b10000001 Y
#291000
0#
b0 %
b101110101101 (
16
0C
b0 F
#300000
0!
0A
#310000
1!
05
07
1A
0J
b0 O
0P
b11 S
b10 T
0U
#311000
b101110101101 (
1,
06
1D
#320000
0!
0A
#330000
1!
05
07
1A
0J
b0 O
0P
b100 S
b11 T
0U
#331000
b101110101101 (
06
#340000
0!
0A
#350000
1!
05
07
1A
0J
b0 O
0P
b101 S
b100 T
0U
#351000
b101110101101 (
06
#360000
0!
0A
#370000
1!
05
07
1A
0J
b0 O
0P
b110 S
b101 T
0U
#371000
b101110101101 (
06
#380000
0!
0A
#390000
1!
05
07
1A
0J
b0 O
0P
b111 S
b110 T
0U
#391000
b101110101101 (
06
#400000
0!
0A
#410000
1!
05
07
1A
0J
b0 O
0P
b1000 S
b111 T
1U
#411000
b101110101101 (
06
#420000
0!
0A
#430000
1!
1/
05
07
1A
0J
1K
b0 O
0P
b1001 S
b1000 T
0U
b0 Z
#431000
b101110101101 (
06
#440000
0!
0A
#450000
1!
05
07
1A
0J
b0 O
0P
b1010 S
b1001 T
0U
#451000
b101110101101 (
06
#460000
0!
0A
#470000
1!
05
07
1A
0J
b0 O
0P
b1011 S
b1010 T
0U
#471000
b101110101101 (
06
#480000
0!
0A
#490000
1!
05
07
1A
0J
b0 O
0P
b1100 S
b1011 T
0U
#491000
b101110101101 (
06
#500000
0!
0A
#510000
1!
05
07
1A
0J
b0 O
0P
b1101 S
b1100 T
0U
#511000
b101110101101 (
06
#520000
0!
0A
#530000
1!
05
07
1A
0J
b0 O
0P
b1110 S
b1101 T
0U
#531000
b101110101101 (
06
#540000
0!
0A
#550000
1!
05
07
1A
0J
b0 O
0P
b1111 S
b1110 T
0U
#551000
b101110101101 (
06
#560000
0!
0A
#570000
1!
05
07
1A
0J
b0 O
0P
b10000 S
b1111 T
0U
#571000
b101110101101 (
06
#580000
0!
0A
#590000
1!
0/
05
07
1A
0J
0K
b0 O
0P
b10001 S
b10000 T
0U
#591000
b101110101101 (
06
#600000
0!
0A
#610000
1!
05
07
1A
0J
b0 O
0P
b10010 S
b10001 T
0U
#611000
b101110101101 (
06
#620000
0!
0A
#630000
1!
05
07
1A
0J
b0 O
0P
b10011 S
b10010 T
0U
#631000
b101110101101 (
06
#640000
0!
0A
#650000
1!
05
07
1A
0J
b0 O
0P
b10100 S
b10011 T
0U
#651000
b101110101101 (
06
#660000
0!
0A
#670000
1!
05
07
1A
0J
b0 O
0P
b10101 S
b10100 T
0U
#671000
b101110101101 (
06
#680000
0!
0A
#690000
1!
05
07
1A
0J
b0 O
0P
b10110 S
b10101 T
0U
#691000
b101110101101 (
06
#700000
0!
0A
#710000
1!
05
07
1A
0J
b0 O
0P
b10111 S
b10110 T
0U
#711000
b101110101101 (
06
#720000
0!
0A
#730000
1!
05
07
1A
0J
b0 O
0P
b11000 S
b10111 T
1U
#731000
b101110101101 (
06
#740000
0!
0A
#750000
1!
1/
05
07
1A
0J
1K
b0 O
0P
b11001 S
b11000 T
0U
b0 Z
#751000
b101110101101 (
06
#760000
0!
0A
#770000
1!
05
07
1A
0J
b0 O
0P
b11010 S
b11001 T
0U
#771000
b101110101101 (
06
#780000
0!
0A
#790000
1!
05
07
1A
0J
b0 O
0P
b11011 S
b11010 T
0U
#791000
b101110101101 (
06
#800000
0!
0A
#810000
1!
05
07
1A
0J
b0 O
0P
b11100 S
b11011 T
0U
#811000
b101110101101 (
06
#820000
0!
0A
#830000
1!
05
07
1A
0J
b0 O
0P
b11101 S
b11100 T
0U
#831000
b101110101101 (
06
#840000
0!
0A
#850000
1!
05
07
1A
0J
b0 O
0P
b11110 S
b11101 T
0U
#851000
b101110101101 (
06
#860000
0!
0A
#870000
1!
05
07
1A
0J
b0 O
0P
b11111 S
b11110 T
0U
#871000
b101110101101 (
06
#880000
0!
0A
#890000
1!
05
07
1A
0J
b0 O
0P
b100000 S
b11111 T
0U
#891000
b101110101101 (
06
#900000
0!
0A
#910000
1!
0/
05
07
1A
0J
0K
b0 O
0P
b100001 S
b100000 T
0U
#911000
b101110101101 (
06
#920000
0!
0A
#930000
1!
05
07
1A
0J
b0 O
0P
b100010 S
b100001 T
0U
#931000
b101110101101 (
06
#940000
0!
0A
#950000
1!
05
07
1A
0J
b0 O
0P
b100011 S
b100010 T
0U
#951000
b101110101101 (
06
#960000
0!
0A
#970000
1!
05
07
1A
0J
b0 O
0P
b100100 S
b100011 T
0U
#971000
b101110101101 (
06
#980000
0!
0A
#990000
1!
05
07
1A
0J
b0 O
0P
b100101 S
b100100 T
0U
#991000
b101110101101 (
06
#1000000
0!
0A
#1010000
1!
05
07
1A
0J
b0 O
0P
b100110 S
b100101 T
0U
#1011000
b101110101101 (
06
#1020000
0!
0A
#1030000
1!
05
07
1A
0J
b0 O
0P
b100111 S
b100110 T
0U
#1031000
b101110101101 (
06
#1040000
0!
0A
#1050000
1!
05
07
1A
0J
b0 O
0P
b101000 S
b100111 T
1U
#1051000
b101110101101 (
06
#1060000
0!
0A
#1070000
1!
1/
05
07
1A
0J
1K
b0 O
0P
b101001 S
b101000 T
0U
b0 Z
#1071000
b101110101101 (
06
#1080000
0!
0A
#1090000
1!
05
07
1A
0J
b0 O
0P
b101010 S
b101001 T
0U
#1091000
b101110101101 (
06
#1100000
0!
0A
#1110000
1!
05
07
1A
0J
b0 O
0P
b101011 S
b101010 T
0U
#1111000
b101110101101 (
06
#1120000
0!
0A
#1130000
1!
05
07
1A
0J
b0 O
0P
b101100 S
b101011 T
0U
#1131000
b101110101101 (
06
#1140000
0!
0A
#1150000
1!
05
07
1A
0J
b0 O
0P
b101101 S
b101100 T
0U
#1151000
b101110101101 (
06
#1160000
0!
0A
#1170000
1!
05
07
1A
0J
b0 O
0P
b101110 S
b101101 T
0U
#1171000
b101110101101 (
06
#1180000
0!
0A
#1190000
1!
05
07
1A
0J
b0 O
0P
b101111 S
b101110 T
0U
#1191000
b101110101101 (
06
#1200000
0!
0A
#1210000
1!
05
07
1A
0J
b0 O
0P
b110000 S
b101111 T
0U
#1211000
b101110101101 (
06
#1220000
0!
0A
#1230000
1!
1.
0/
05
07
1A
1J
0K
1L
b0 O
0P
b110001 S
b110000 T
0U
#1231000
b101110101101 (
06
#1240000
0!
0A
#1250000
1!
05
07
1A
1J
b0 O
0P
b110010 S
b110001 T
0U
#1251000
b101110101101 (
06
#1260000
0!
0A
#1270000
1!
05
07
1A
1J
b0 O
0P
b110011 S
b110010 T
0U
#1271000
b101110101101 (
06
#1280000
0!
0A
#1290000
1!
05
07
1A
1J
b0 O
0P
b110100 S
b110011 T
0U
#1291000
b101110101101 (
06
#1300000
0!
0A
#1310000
1!
05
07
1A
1J
b0 O
0P
b110101 S
b110100 T
0U
#1311000
b101110101101 (
06
#1320000
0!
0A
#1330000
1!
05
07
1A
1J
b0 O
0P
b110110 S
b110101 T
0U
#1331000
b101110101101 (
06
#1340000
0!
0A
#1350000
1!
05
07
1A
1J
b0 O
0P
b110111 S
b110110 T
0U
#1351000
b101110101101 (
06
#1360000
0!
0A
#1370000
1!
05
07
1A
1J
b0 O
0P
b111000 S
b110111 T
1U
#1371000
b101110101101 (
06
#1380000
0!
0A
#1390000
1!
1/
05
07
1A
1J
1K
b0 O
0P
b111001 S
b111000 T
0U
b10000001 Y
b1 Z
#1391000
b101110101101 (
06
#1400000
0!
0A
#1410000
1!
05
07
1A
1J
b0 O
0P
b111010 S
b111001 T
0U
#1411000
b101110101101 (
06
#1420000
0!
0A
#1430000
1!
05
07
1A
1J
b0 O
0P
b111011 S
b111010 T
0U
#1431000
b101110101101 (
06
#1440000
0!
0A
#1450000
1!
05
07
1A
1J
b0 O
0P
b111100 S
b111011 T
0U
#1451000
b101110101101 (
06
#1460000
0!
0A
#1470000
1!
05
07
1A
1J
b0 O
0P
b111101 S
b111100 T
0U
#1471000
b101110101101 (
06
#1480000
0!
0A
#1490000
1!
05
07
1A
1J
b0 O
0P
b111110 S
b111101 T
0U
#1491000
b101110101101 (
06
#1500000
0!
0A
#1510000
1!
05
07
1A
1J
b0 O
0P
b111111 S
b111110 T
0U
#1511000
b101110101101 (
06
#1520000
0!
0A
#1530000
1!
05
07
1A
1J
b0 O
0P
b1000000 S
b111111 T
0U
#1531000
b101110101101 (
06
#1540000
0!
0A
#1550000
1!
0.
0/
05
07
1A
0J
0K
0L
b0 O
0P
b1000001 S
b1000000 T
0U
#1551000
b101110101101 (
06
#1560000
0!
0A
#1570000
1!
05
07
1A
0J
b0 O
0P
b1000010 S
b1000001 T
0U
#1571000
b101110101101 (
06
#1580000
0!
0A
#1590000
1!
05
07
1A
0J
b0 O
0P
b1000011 S
b1000010 T
0U
#1591000
b101110101101 (
06
#1600000
0!
0A
#1610000
1!
05
07
1A
0J
b0 O
0P
b1000100 S
b1000011 T
0U
#1611000
b101110101101 (
06
#1620000
0!
0A
#1630000
1!
05
07
1A
0J
b0 O
0P
b1000101 S
b1000100 T
0U
#1631000
b101110101101 (
06
#1640000
0!
0A
#1650000
1!
05
07
1A
0J
b0 O
0P
b1000110 S
b1000101 T
0U
#1651000
b101110101101 (
06
#1660000
0!
0A
#1670000
1!
05
07
1A
0J
b0 O
0P
b1000111 S
b1000110 T
0U
#1671000
b101110101101 (
06
#1680000
0!
0A
#1690000
1!
05
07
1A
0J
b0 O
0P
b1001000 S
b1000111 T
1U
#1691000
b101110101101 (
06
#1700000
0!
0A
#1710000
1!
1/
05
07
1A
0J
1K
b0 O
0P
b1001001 S
b1001000 T
0U
b10000001 Y
b10 Z
#1711000
b101110101101 (
06
#1720000
0!
0A
#1730000
1!
05
07
1A
0J
b0 O
0P
b1001010 S
b1001001 T
0U
#1731000
b101110101101 (
06
#1740000
0!
0A
#1750000
1!
05
07
1A
0J
b0 O
0P
b1001011 S
b1001010 T
0U
#1751000
b101110101101 (
06
#1760000
0!
0A
#1770000
1!
05
07
1A
0J
b0 O
0P
b1001100 S
b1001011 T
0U
#1771000
b101110101101 (
06
#1780000
0!
0A
#1790000
1!
05
07
1A
0J
b0 O
0P
b1001101 S
b1001100 T
0U
#1791000
b101110101101 (
06
#1800000
0!
0A
#1810000
1!
05
07
1A
0J
b0 O
0P
b1001110 S
b1001101 T
0U
#1811000
b101110101101 (
06
#1820000
0!
0A
#1830000
1!
05
07
1A
0J
b0 O
0P
b1001111 S
b1001110 T
0U
#1831000
b101110101101 (
06
#1840000
0!
0A
#1850000
1!
05
07
1A
0J
b0 O
0P
b1010000 S
b1001111 T
0U
#1851000
b101110101101 (
06
#1860000
0!
0A
#1870000
1!
1.
0/
05
07
1A
1J
0K
1L
b0 O
0P
b1010001 S
b1010000 T
0U
#1871000
b101110101101 (
06
#1880000
0!
0A
#1890000
1!
05
07
1A
1J
b0 O
0P
b1010010 S
b1010001 T
0U
#1891000
b101110101101 (
06
#1900000
0!
0A
#1910000
1!
05
07
1A
1J
b0 O
0P
b1010011 S
b1010010 T
0U
#1911000
b101110101101 (
06
#1920000
0!
0A
#1930000
1!
05
07
1A
1J
b0 O
0P
b1010100 S
b1010011 T
0U
#1931000
b101110101101 (
06
#1940000
0!
0A
#1950000
1!
05
07
1A
1J
b0 O
0P
b1010101 S
b1010100 T
0U
#1951000
b101110101101 (
06
#1960000
0!
0A
#1970000
1!
05
07
1A
1J
b0 O
0P
b1010110 S
b1010101 T
0U
#1971000
b101110101101 (
06
#1980000
0!
0A
#1990000
1!
05
07
1A
1J
b0 O
0P
b1010111 S
b1010110 T
0U
#1991000
b101110101101 (
06
#2000000
0!
0A
#2010000
1!
05
07
1A
1J
b0 O
0P
b1011000 S
b1010111 T
1U
#2011000
b101110101101 (
06
#2020000
0!
0A
#2030000
1!
1/
05
07
1A
1J
1K
b0 O
0P
b1011001 S
b1011000 T
0U
b10000001 Y
b101 Z
#2031000
b101110101101 (
06
#2040000
0!
0A
#2050000
1!
05
07
1A
1J
b0 O
0P
b1011010 S
b1011001 T
0U
#2051000
b101110101101 (
06
#2060000
0!
0A
#2070000
1!
05
07
1A
1J
b0 O
0P
b1011011 S
b1011010 T
0U
#2071000
b101110101101 (
06
#2080000
0!
0A
#2090000
1!
05
07
1A
1J
b0 O
0P
b1011100 S
b1011011 T
0U
#2091000
b101110101101 (
06
#2100000
0!
0A
#2110000
1!
05
07
1A
1J
b0 O
0P
b1011101 S
b1011100 T
0U
#2111000
b101110101101 (
06
#2120000
0!
0A
#2130000
1!
05
07
1A
1J
b0 O
0P
b1011110 S
b1011101 T
0U
#2131000
b101110101101 (
06
#2140000
0!
0A
